[{
        "teamId": "30",
        "fullName": "Sacramento Kings",
        "fastBreakPoints": "20.30",
        "pointsInPaint": "50.05",
        "biggestLead": "11.61",
        "secondChancePoints": "13.27",
        "pointsOffTurnovers": "18.63",
        "longestRun": "10.46",
        "fgm": "41.66",
        "fga": "89.91",
        "fgp": "44.70",
        "ftm": "15.82",
        "fta": "21.84",
        "ftp": "69.13",
        "tpm": "10.83",
        "tpa": "28.82",
        "tpp": "36.13",
        "offReb": "10.72",
        "defReb": "32.95",
        "assists": "24.43",
        "pFouls": "20.46",
        "steals": "8.01",
        "turnovers": "12.44",
        "blocks": "4.29",
        "plusMinus": "-1.43"
    },
    {
        "teamId": "11",
        "fullName": "Golden State Warriors",
        "fastBreakPoints": "17.68",
        "pointsInPaint": "40.29",
        "biggestLead": "15.51",
        "secondChancePoints": "11.88",
        "pointsOffTurnovers": "15.23",
        "longestRun": "10.04",
        "fgm": "40.94",
        "fga": "83.21",
        "fgp": "45.67",
        "ftm": "15.38",
        "fta": "19.07",
        "ftp": "74.92",
        "tpm": "12.20",
        "tpa": "31.68",
        "tpp": "35.68",
        "offReb": "9.16",
        "defReb": "33.74",
        "assists": "27.18",
        "pFouls": "19.84",
        "steals": "6.95",
        "turnovers": "12.77",
        "blocks": "5.96",
        "plusMinus": "6.27"
    },
    {
        "teamId": "2",
        "fullName": "Boston Celtics",
        "fastBreakPoints": "15.85",
        "pointsInPaint": "43.73",
        "biggestLead": "15.05",
        "secondChancePoints": "11.98",
        "pointsOffTurnovers": "17.79",
        "longestRun": "11.01",
        "fgm": "41.16",
        "fga": "88.20",
        "fgp": "45.61",
        "ftm": "15.20",
        "fta": "18.90",
        "ftp": "78.77",
        "tpm": "12.38",
        "tpa": "33.67",
        "tpp": "35.69",
        "offReb": "9.49",
        "defReb": "33.90",
        "assists": "25.63",
        "pFouls": "20.00",
        "steals": "8.44",
        "turnovers": "12.23",
        "blocks": "5.17",
        "plusMinus": "4.77"
    },
    {
        "teamId": "8",
        "fullName": "Dallas Mavericks",
        "fastBreakPoints": "11.90",
        "pointsInPaint": "43.37",
        "biggestLead": "11.10",
        "secondChancePoints": "12.66",
        "pointsOffTurnovers": "14.29",
        "longestRun": "9.88",
        "fgm": "37.79",
        "fga": "84.71",
        "fgp": "43.61",
        "ftm": "18.07",
        "fta": "24.40",
        "ftp": "72.23",
        "tpm": "12.18",
        "tpa": "35.79",
        "tpp": "33.27",
        "offReb": "9.91",
        "defReb": "34.23",
        "assists": "22.76",
        "pFouls": "19.60",
        "steals": "6.33",
        "turnovers": "13.39",
        "blocks": "4.21",
        "plusMinus": "-1.38"
    },
    {
        "teamId": "41",
        "fullName": "Washington Wizards",
        "fastBreakPoints": "14.10",
        "pointsInPaint": "50.07",
        "biggestLead": "9.74",
        "secondChancePoints": "12.40",
        "pointsOffTurnovers": "17.67",
        "longestRun": "10.84",
        "fgm": "42.15",
        "fga": "90.11",
        "fgp": "46.81",
        "ftm": "18.39",
        "fta": "23.94",
        "ftp": "76.52",
        "tpm": "11.34",
        "tpa": "33.32",
        "tpp": "33.91",
        "offReb": "9.68",
        "defReb": "32.63",
        "assists": "26.27",
        "pFouls": "20.74",
        "steals": "8.35",
        "turnovers": "13.65",
        "blocks": "4.62",
        "plusMinus": "-2.90"
    },
    {
        "teamId": "14",
        "fullName": "Houston Rockets",
        "fastBreakPoints": "11.67",
        "pointsInPaint": "41.05",
        "biggestLead": "16.04",
        "secondChancePoints": "12.94",
        "pointsOffTurnovers": "17.55",
        "longestRun": "10.66",
        "fgm": "38.27",
        "fga": "85.52",
        "fgp": "43.78",
        "ftm": "18.62",
        "fta": "23.60",
        "ftp": "77.20",
        "tpm": "15.74",
        "tpa": "44.40",
        "tpp": "34.39",
        "offReb": "10.07",
        "defReb": "31.11",
        "assists": "20.67",
        "pFouls": "21.48",
        "steals": "8.27",
        "turnovers": "12.29",
        "blocks": "4.83",
        "plusMinus": "4.55"
    },
    {
        "teamId": "7",
        "fullName": "Cleveland Cavaliers",
        "fastBreakPoints": "10.27",
        "pointsInPaint": "43.51",
        "biggestLead": "7.67",
        "secondChancePoints": "13.26",
        "pointsOffTurnovers": "13.96",
        "longestRun": "9.76",
        "fgm": "37.85",
        "fga": "85.39",
        "fgp": "43.30",
        "ftm": "15.91",
        "fta": "20.15",
        "ftp": "76.44",
        "tpm": "10.04",
        "tpa": "28.44",
        "tpp": "34.13",
        "offReb": "10.49",
        "defReb": "31.18",
        "assists": "20.22",
        "pFouls": "19.56",
        "steals": "6.38",
        "turnovers": "12.52",
        "blocks": "2.32",
        "plusMinus": "-9.65"
    },
    {
        "teamId": "31",
        "fullName": "San Antonio Spurs",
        "fastBreakPoints": "9.89",
        "pointsInPaint": "41.22",
        "biggestLead": "12.11",
        "secondChancePoints": "11.00",
        "pointsOffTurnovers": "13.45",
        "longestRun": "10.32",
        "fgm": "40.18",
        "fga": "84.06",
        "fgp": "45.59",
        "ftm": "16.44",
        "fta": "20.12",
        "ftp": "77.81",
        "tpm": "9.51",
        "tpa": "24.12",
        "tpp": "38.00",
        "offReb": "8.78",
        "defReb": "33.68",
        "assists": "23.28",
        "pFouls": "17.35",
        "steals": "5.87",
        "turnovers": "11.39",
        "blocks": "4.45",
        "plusMinus": "1.07"
    },
    {
        "teamId": "15",
        "fullName": "Indiana Pacers",
        "fastBreakPoints": "13.85",
        "pointsInPaint": "46.59",
        "biggestLead": "13.37",
        "secondChancePoints": "12.85",
        "pointsOffTurnovers": "18.13",
        "longestRun": "10.07",
        "fgm": "39.35",
        "fga": "82.91",
        "fgp": "45.26",
        "ftm": "15.06",
        "fta": "20.04",
        "ftp": "71.70",
        "tpm": "9.00",
        "tpa": "24.12",
        "tpp": "35.31",
        "offReb": "8.94",
        "defReb": "32.21",
        "assists": "24.51",
        "pFouls": "18.45",
        "steals": "8.29",
        "turnovers": "12.62",
        "blocks": "4.66",
        "plusMinus": "3.40"
    },
    {
        "teamId": "29",
        "fullName": "Portland Trail Blazers",
        "fastBreakPoints": "10.62",
        "pointsInPaint": "47.27",
        "biggestLead": "14.34",
        "secondChancePoints": "14.40",
        "pointsOffTurnovers": "14.41",
        "longestRun": "10.00",
        "fgm": "40.71",
        "fga": "87.18",
        "fgp": "45.16",
        "ftm": "18.39",
        "fta": "22.51",
        "ftp": "78.59",
        "tpm": "10.61",
        "tpa": "29.49",
        "tpp": "34.94",
        "offReb": "11.32",
        "defReb": "34.91",
        "assists": "22.13",
        "pFouls": "19.73",
        "steals": "6.38",
        "turnovers": "12.76",
        "blocks": "4.80",
        "plusMinus": "4.27"
    },
    {
        "teamId": "26",
        "fullName": "Orlando Magic",
        "fastBreakPoints": "10.82",
        "pointsInPaint": "44.07",
        "biggestLead": "13.78",
        "secondChancePoints": "12.37",
        "pointsOffTurnovers": "15.24",
        "longestRun": "10.60",
        "fgm": "40.44",
        "fga": "89.11",
        "fgp": "45.43",
        "ftm": "15.01",
        "fta": "19.21",
        "ftp": "78.20",
        "tpm": "11.43",
        "tpa": "32.11",
        "tpp": "35.69",
        "offReb": "10.04",
        "defReb": "35.39",
        "assists": "25.55",
        "pFouls": "18.61",
        "steals": "6.62",
        "turnovers": "12.66",
        "blocks": "5.48",
        "plusMinus": "0.71"
    },
    {
        "teamId": "9",
        "fullName": "Denver Nuggets",
        "fastBreakPoints": "12.30",
        "pointsInPaint": "50.95",
        "biggestLead": "13.87",
        "secondChancePoints": "15.27",
        "pointsOffTurnovers": "15.37",
        "longestRun": "10.27",
        "fgm": "40.91",
        "fga": "87.88",
        "fgp": "45.54",
        "ftm": "15.52",
        "fta": "20.59",
        "ftp": "74.38",
        "tpm": "10.74",
        "tpa": "30.60",
        "tpp": "34.12",
        "offReb": "11.61",
        "defReb": "33.68",
        "assists": "26.78",
        "pFouls": "19.48",
        "steals": "7.50",
        "turnovers": "12.52",
        "blocks": "4.27",
        "plusMinus": "4.00"
    },
    {
        "teamId": "5",
        "fullName": "Charlotte Hornets",
        "fastBreakPoints": "11.35",
        "pointsInPaint": "45.68",
        "biggestLead": "11.87",
        "secondChancePoints": "12.63",
        "pointsOffTurnovers": "15.85",
        "longestRun": "10.52",
        "fgm": "39.12",
        "fga": "87.79",
        "fgp": "43.54",
        "ftm": "17.84",
        "fta": "22.40",
        "ftp": "77.27",
        "tpm": "11.57",
        "tpa": "33.15",
        "tpp": "34.07",
        "offReb": "9.72",
        "defReb": "33.01",
        "assists": "22.57",
        "pFouls": "18.35",
        "steals": "7.02",
        "turnovers": "11.34",
        "blocks": "4.83",
        "plusMinus": "-1.48"
    },
    {
        "teamId": "16",
        "fullName": "LA Clippers",
        "fastBreakPoints": "13.91",
        "pointsInPaint": "49.98",
        "biggestLead": "12.48",
        "secondChancePoints": "12.70",
        "pointsOffTurnovers": "14.96",
        "longestRun": "10.63",
        "fgm": "40.23",
        "fga": "85.24",
        "fgp": "46.10",
        "ftm": "22.09",
        "fta": "27.87",
        "ftp": "77.09",
        "tpm": "9.74",
        "tpa": "25.04",
        "tpp": "37.92",
        "offReb": "9.37",
        "defReb": "34.99",
        "assists": "23.37",
        "pFouls": "22.78",
        "steals": "6.56",
        "turnovers": "13.46",
        "blocks": "4.60",
        "plusMinus": "0.74"
    },
    {
        "teamId": "25",
        "fullName": "Oklahoma City Thunder",
        "fastBreakPoints": "17.93",
        "pointsInPaint": "51.02",
        "biggestLead": "12.76",
        "secondChancePoints": "15.29",
        "pointsOffTurnovers": "18.93",
        "longestRun": "10.94",
        "fgm": "42.02",
        "fga": "92.68",
        "fgp": "44.90",
        "ftm": "17.72",
        "fta": "24.80",
        "ftp": "70.75",
        "tpm": "11.21",
        "tpa": "32.22",
        "tpp": "34.68",
        "offReb": "12.35",
        "defReb": "34.96",
        "assists": "23.02",
        "pFouls": "22.15",
        "steals": "9.23",
        "turnovers": "13.52",
        "blocks": "5.12",
        "plusMinus": "3.06"
    },
    {
        "teamId": "23",
        "fullName": "New Orleans Pelicans",
        "fastBreakPoints": "14.83",
        "pointsInPaint": "58.22",
        "biggestLead": "10.49",
        "secondChancePoints": "14.34",
        "pointsOffTurnovers": "16.10",
        "longestRun": "10.32",
        "fgm": "43.67",
        "fga": "92.23",
        "fgp": "47.46",
        "ftm": "17.83",
        "fta": "23.43",
        "ftp": "75.75",
        "tpm": "10.27",
        "tpa": "29.87",
        "tpp": "34.41",
        "offReb": "11.10",
        "defReb": "36.21",
        "assists": "27.02",
        "pFouls": "21.12",
        "steals": "7.44",
        "turnovers": "14.49",
        "blocks": "5.38",
        "plusMinus": "-1.33"
    },
    {
        "teamId": "10",
        "fullName": "Detroit Pistons",
        "fastBreakPoints": "9.84",
        "pointsInPaint": "43.73",
        "biggestLead": "11.68",
        "secondChancePoints": "12.78",
        "pointsOffTurnovers": "15.33",
        "longestRun": "10.54",
        "fgm": "37.84",
        "fga": "86.09",
        "fgp": "42.99",
        "ftm": "16.71",
        "fta": "22.38",
        "ftp": "73.35",
        "tpm": "11.70",
        "tpa": "33.87",
        "tpp": "33.50",
        "offReb": "11.00",
        "defReb": "32.95",
        "assists": "21.96",
        "pFouls": "21.51",
        "steals": "6.78",
        "turnovers": "12.62",
        "blocks": "3.98",
        "plusMinus": "-0.13"
    },
    {
        "teamId": "28",
        "fullName": "Phoenix Suns",
        "fastBreakPoints": "14.74",
        "pointsInPaint": "47.85",
        "biggestLead": "7.11",
        "secondChancePoints": "11.65",
        "pointsOffTurnovers": "17.49",
        "longestRun": "9.87",
        "fgm": "38.61",
        "fga": "84.04",
        "fgp": "44.33",
        "ftm": "16.94",
        "fta": "21.82",
        "ftp": "74.65",
        "tpm": "9.27",
        "tpa": "28.04",
        "tpp": "31.67",
        "offReb": "8.84",
        "defReb": "30.26",
        "assists": "22.96",
        "pFouls": "22.74",
        "steals": "8.65",
        "turnovers": "14.76",
        "blocks": "4.90",
        "plusMinus": "-8.89"
    },
    {
        "teamId": "22",
        "fullName": "Minnesota Timberwolves",
        "fastBreakPoints": "11.24",
        "pointsInPaint": "47.22",
        "biggestLead": "11.01",
        "secondChancePoints": "14.21",
        "pointsOffTurnovers": "16.57",
        "longestRun": "9.87",
        "fgm": "39.67",
        "fga": "86.94",
        "fgp": "43.52",
        "ftm": "18.07",
        "fta": "22.98",
        "ftp": "74.72",
        "tpm": "9.63",
        "tpa": "27.24",
        "tpp": "34.05",
        "offReb": "10.61",
        "defReb": "31.91",
        "assists": "23.46",
        "pFouls": "19.41",
        "steals": "7.99",
        "turnovers": "11.91",
        "blocks": "4.87",
        "plusMinus": "-1.15"
    },
    {
        "teamId": "20",
        "fullName": "Miami Heat",
        "fastBreakPoints": "9.91",
        "pointsInPaint": "48.93",
        "biggestLead": "13.18",
        "secondChancePoints": "14.15",
        "pointsOffTurnovers": "15.52",
        "longestRun": "11.29",
        "fgm": "39.65",
        "fga": "88.04",
        "fgp": "45.18",
        "ftm": "15.10",
        "fta": "21.73",
        "ftp": "68.92",
        "tpm": "11.32",
        "tpa": "32.40",
        "tpp": "35.07",
        "offReb": "11.26",
        "defReb": "35.11",
        "assists": "24.28",
        "pFouls": "20.88",
        "steals": "7.65",
        "turnovers": "14.09",
        "blocks": "5.46",
        "plusMinus": "-0.23"
    },
    {
        "teamId": "40",
        "fullName": "Utah Jazz",
        "fastBreakPoints": "10.37",
        "pointsInPaint": "48.90",
        "biggestLead": "16.27",
        "secondChancePoints": "12.85",
        "pointsOffTurnovers": "15.93",
        "longestRun": "10.61",
        "fgm": "39.49",
        "fga": "84.22",
        "fgp": "45.80",
        "ftm": "18.28",
        "fta": "24.80",
        "ftp": "72.11",
        "tpm": "11.73",
        "tpa": "32.99",
        "tpp": "34.55",
        "offReb": "9.70",
        "defReb": "35.61",
        "assists": "25.41",
        "pFouls": "20.57",
        "steals": "7.89",
        "turnovers": "14.48",
        "blocks": "5.71",
        "plusMinus": "5.29"
    },
    {
        "teamId": "17",
        "fullName": "Los Angeles Lakers",
        "fastBreakPoints": "18.88",
        "pointsInPaint": "53.56",
        "biggestLead": "10.65",
        "secondChancePoints": "12.43",
        "pointsOffTurnovers": "16.41",
        "longestRun": "10.32",
        "fgm": "41.12",
        "fga": "87.32",
        "fgp": "45.43",
        "ftm": "15.68",
        "fta": "22.32",
        "ftp": "67.50",
        "tpm": "10.06",
        "tpa": "30.00",
        "tpp": "32.10",
        "offReb": "9.79",
        "defReb": "34.90",
        "assists": "24.73",
        "pFouls": "20.15",
        "steals": "7.35",
        "turnovers": "14.60",
        "blocks": "5.16",
        "plusMinus": "-1.32"
    },
    {
        "teamId": "1",
        "fullName": "Atlanta Hawks",
        "fastBreakPoints": "14.22",
        "pointsInPaint": "47.88",
        "biggestLead": "8.56",
        "secondChancePoints": "13.38",
        "pointsOffTurnovers": "15.89",
        "longestRun": "10.01",
        "fgm": "38.68",
        "fga": "86.11",
        "fgp": "42.28",
        "ftm": "16.60",
        "fta": "22.05",
        "ftp": "70.58",
        "tpm": "12.12",
        "tpa": "34.55",
        "tpp": "32.90",
        "offReb": "10.99",
        "defReb": "32.46",
        "assists": "24.11",
        "pFouls": "22.18",
        "steals": "7.71",
        "turnovers": "15.82",
        "blocks": "4.80",
        "plusMinus": "-5.82"
    },
    {
        "teamId": "19",
        "fullName": "Memphis Grizzlies",
        "fastBreakPoints": "11.68",
        "pointsInPaint": "44.29",
        "biggestLead": "10.74",
        "secondChancePoints": "10.72",
        "pointsOffTurnovers": "16.66",
        "longestRun": "10.32",
        "fgm": "36.13",
        "fga": "80.30",
        "fgp": "42.91",
        "ftm": "16.74",
        "fta": "21.83",
        "ftp": "73.27",
        "tpm": "9.32",
        "tpa": "27.26",
        "tpp": "32.31",
        "offReb": "8.52",
        "defReb": "31.28",
        "assists": "22.74",
        "pFouls": "20.87",
        "steals": "8.02",
        "turnovers": "12.70",
        "blocks": "5.17",
        "plusMinus": "-2.12"
    },
    {
        "teamId": "27",
        "fullName": "Philadelphia 76ers",
        "fastBreakPoints": "14.49",
        "pointsInPaint": "47.49",
        "biggestLead": "14.72",
        "secondChancePoints": "13.35",
        "pointsOffTurnovers": "14.90",
        "longestRun": "10.21",
        "fgm": "40.01",
        "fga": "84.87",
        "fgp": "45.51",
        "ftm": "20.27",
        "fta": "26.24",
        "ftp": "74.32",
        "tpm": "10.43",
        "tpa": "29.15",
        "tpp": "34.40",
        "offReb": "10.26",
        "defReb": "35.62",
        "assists": "26.01",
        "pFouls": "20.50",
        "steals": "7.13",
        "turnovers": "13.88",
        "blocks": "5.15",
        "plusMinus": "2.85"
    },
    {
        "teamId": "21",
        "fullName": "Milwaukee Bucks",
        "fastBreakPoints": "17.44",
        "pointsInPaint": "52.46",
        "biggestLead": "17.29",
        "secondChancePoints": "11.37",
        "pointsOffTurnovers": "16.39",
        "longestRun": "10.82",
        "fgm": "42.66",
        "fga": "89.78",
        "fgp": "47.04",
        "ftm": "17.77",
        "fta": "23.01",
        "ftp": "76.18",
        "tpm": "13.29",
        "tpa": "37.67",
        "tpp": "34.92",
        "offReb": "9.12",
        "defReb": "39.89",
        "assists": "25.63",
        "pFouls": "19.33",
        "steals": "7.39",
        "turnovers": "13.10",
        "blocks": "5.90",
        "plusMinus": "8.34"
    },
    {
        "teamId": "24",
        "fullName": "New York Knicks",
        "fastBreakPoints": "10.55",
        "pointsInPaint": "42.12",
        "biggestLead": "7.12",
        "secondChancePoints": "12.59",
        "pointsOffTurnovers": "14.16",
        "longestRun": "9.73",
        "fgm": "36.35",
        "fga": "84.17",
        "fgp": "41.15",
        "ftm": "17.46",
        "fta": "22.98",
        "ftp": "72.52",
        "tpm": "9.45",
        "tpa": "28.22",
        "tpp": "31.75",
        "offReb": "10.04",
        "defReb": "32.46",
        "assists": "19.04",
        "pFouls": "19.85",
        "steals": "6.54",
        "turnovers": "12.57",
        "blocks": "4.84",
        "plusMinus": "-8.84"
    },
    {
        "teamId": "6",
        "fullName": "Chicago Bulls",
        "fastBreakPoints": "11.65",
        "pointsInPaint": "49.39",
        "biggestLead": "7.89",
        "secondChancePoints": "10.62",
        "pointsOffTurnovers": "14.73",
        "longestRun": "10.04",
        "fgm": "38.70",
        "fga": "85.78",
        "fgp": "44.09",
        "ftm": "15.74",
        "fta": "20.12",
        "ftp": "76.83",
        "tpm": "8.85",
        "tpa": "25.28",
        "tpp": "33.99",
        "offReb": "8.59",
        "defReb": "33.32",
        "assists": "21.27",
        "pFouls": "19.80",
        "steals": "7.18",
        "turnovers": "13.12",
        "blocks": "4.21",
        "plusMinus": "-8.45"
    },
    {
        "teamId": "38",
        "fullName": "Toronto Raptors",
        "fastBreakPoints": "18.27",
        "pointsInPaint": "47.76",
        "biggestLead": "15.72",
        "secondChancePoints": "12.30",
        "pointsOffTurnovers": "17.06",
        "longestRun": "10.55",
        "fgm": "41.61",
        "fga": "87.99",
        "fgp": "46.94",
        "ftm": "17.46",
        "fta": "21.71",
        "ftp": "79.94",
        "tpm": "12.24",
        "tpa": "33.44",
        "tpp": "36.05",
        "offReb": "9.41",
        "defReb": "35.10",
        "assists": "25.02",
        "pFouls": "20.77",
        "steals": "8.22",
        "turnovers": "13.11",
        "blocks": "5.30",
        "plusMinus": "5.89"
    },
    {
        "teamId": "4",
        "fullName": "Brooklyn Nets",
        "fastBreakPoints": "10.98",
        "pointsInPaint": "46.98",
        "biggestLead": "12.33",
        "secondChancePoints": "13.28",
        "pointsOffTurnovers": "14.74",
        "longestRun": "10.13",
        "fgm": "38.74",
        "fga": "86.29",
        "fgp": "43.35",
        "ftm": "18.35",
        "fta": "24.63",
        "ftp": "71.98",
        "tpm": "12.29",
        "tpa": "34.74",
        "tpp": "34.05",
        "offReb": "10.39",
        "defReb": "34.41",
        "assists": "22.95",
        "pFouls": "20.62",
        "steals": "6.32",
        "turnovers": "13.89",
        "blocks": "3.98",
        "plusMinus": "-0.11"
    }
]